[{"season": 2024, "team": "Wisconsin", "conference": "Big Ten", "statName": "firstDowns", "statValue": 225}, {"season": 2024, "team": "Wisconsin", "conference": "Big Ten", "statName": "firstDownsOpponent", "statValue": 219}, {"season": 2024, "team": "Wisconsin", "conference": "Big Ten", "statName": "fourthDownConversions", "statValue": 12}, {"season": 2024, "team": "Wisconsin", "conference": "Big Ten", "statName": "fourthDownConversionsOpponent", "statValue": 8}, {"season": 2024, "team": "Wisconsin", "conference": "Big Ten", "statName": "fourthDowns", "statValue": 20}, {"season": 2024, "team": "Wisconsin", "conference": "Big Ten", "statName": "fourthDownsOpponent", "statValue": 15}, {"season": 2024, "team": "Wisconsin", "conference": "Big Ten", "statName": "fumblesLost", "statValue": 8}, {"season": 2024, "team": "Wisconsin", "conference": "Big Ten", "statName": "fumblesLostOpponent", "statValue": 8}, {"season": 2024, "team": "Wisconsin", "conference": "Big Ten", "statName": "fumblesRecovered", "statValue": 8}, {"season": 2024, "team": "Wisconsin", "conference": "Big Ten", "statName": "fumblesRecoveredOpponent", "statValue": 8}, {"season": 2024, "team": "Wisconsin", "conference": "Big Ten", "statName": "games", "statValue": 12}, {"season": 2024, "team": "Wisconsin", "conference": "Big Ten", "statName": "interceptions", "statValue": 10}, {"season": 2024, "team": "Wisconsin", "conference": "Big Ten", "statName": "interceptionsOpponent", "statValue": 4}, {"season": 2024, "team": "Wisconsin", "conference": "Big Ten", "statName": "interceptionTDs", "statValue": 0}, {"season": 2024, "team": "Wisconsin", "conference": "Big Ten", "statName": "interceptionTDsOpponent", "statValue": 2}, {"season": 2024, "team": "Wisconsin", "conference": "Big Ten", "statName": "interceptionYards", "statValue": 18}, {"season": 2024, "team": "Wisconsin", "conference": "Big Ten", "statName": "interceptionYardsOpponent", "statValue": 134}, {"season": 2024, "team": "Wisconsin", "conference": "Big Ten", "statName": "kickReturns", "statValue": 26}, {"season": 2024, "team": "Wisconsin", "conference": "Big Ten", "statName": "kickReturnsOpponent", "statValue": 13}, {"season": 2024, "team": "Wisconsin", "conference": "Big Ten", "statName": "kickReturnTDs", "statValue": 0}, {"season": 2024, "team": "Wisconsin", "conference": "Big Ten", "statName": "kickReturnTDsOpponent", "statValue": 0}, {"season": 2024, "team": "Wisconsin", "conference": "Big Ten", "statName": "kickReturnYards", "statValue": 636}, {"season": 2024, "team": "Wisconsin", "conference": "Big Ten", "statName": "kickReturnYardsOpponent", "statValue": 262}, {"season": 2024, "team": "Wisconsin", "conference": "Big Ten", "statName": "netPassingYards", "statValue": 2360}, {"season": 2024, "team": "Wisconsin", "conference": "Big Ten", "statName": "netPassingYardsOpponent", "statValue": 2132}, {"season": 2024, "team": "Wisconsin", "conference": "Big Ten", "statName": "passAttempts", "statValue": 365}, {"season": 2024, "team": "Wisconsin", "conference": "Big Ten", "statName": "passAttemptsOpponent", "statValue": 323}, {"season": 2024, "team": "Wisconsin", "conference": "Big Ten", "statName": "passCompletions", "statValue": 208}, {"season": 2024, "team": "Wisconsin", "conference": "Big Ten", "statName": "passCompletionsOpponent", "statValue": 202}, {"season": 2024, "team": "Wisconsin", "conference": "Big Ten", "statName": "passesIntercepted", "statValue": 4}, {"season": 2024, "team": "Wisconsin", "conference": "Big Ten", "statName": "passesInterceptedOpponent", "statValue": 10}, {"season": 2024, "team": "Wisconsin", "conference": "Big Ten", "statName": "passingTDs", "statValue": 14}, {"season": 2024, "team": "Wisconsin", "conference": "Big Ten", "statName": "passingTDsOpponent", "statValue": 12}, {"season": 2024, "team": "Wisconsin", "conference": "Big Ten", "statName": "penalties", "statValue": 63}, {"season": 2024, "team": "Wisconsin", "conference": "Big Ten", "statName": "penaltiesOpponent", "statValue": 68}, {"season": 2024, "team": "Wisconsin", "conference": "Big Ten", "statName": "penaltyYards", "statValue": 450}, {"season": 2024, "team": "Wisconsin", "conference": "Big Ten", "statName": "penaltyYardsOpponent", "statValue": 559}, {"season": 2024, "team": "Wisconsin", "conference": "Big Ten", "statName": "possessionTime", "statValue": 21132}, {"season": 2024, "team": "Wisconsin", "conference": "Big Ten", "statName": "possessionTimeOpponent", "statValue": 22068}, {"season": 2024, "team": "Wisconsin", "conference": "Big Ten", "statName": "puntReturns", "statValue": 16}, {"season": 2024, "team": "Wisconsin", "conference": "Big Ten", "statName": "puntReturnsOpponent", "statValue": 19}, {"season": 2024, "team": "Wisconsin", "conference": "Big Ten", "statName": "puntReturnTDs", "statValue": 0}, {"season": 2024, "team": "Wisconsin", "conference": "Big Ten", "statName": "puntReturnTDsOpponent", "statValue": 0}, {"season": 2024, "team": "Wisconsin", "conference": "Big Ten", "statName": "puntReturnYards", "statValue": 97}, {"season": 2024, "team": "Wisconsin", "conference": "Big Ten", "statName": "puntReturnYardsOpponent", "statValue": 89}, {"season": 2024, "team": "Wisconsin", "conference": "Big Ten", "statName": "rushingAttempts", "statValue": 419}, {"season": 2024, "team": "Wisconsin", "conference": "Big Ten", "statName": "rushingAttemptsOpponent", "statValue": 424}, {"season": 2024, "team": "Wisconsin", "conference": "Big Ten", "statName": "rushingTDs", "statValue": 19}, {"season": 2024, "team": "Wisconsin", "conference": "Big Ten", "statName": "rushingTDsOpponent", "statValue": 20}, {"season": 2024, "team": "Wisconsin", "conference": "Big Ten", "statName": "rushingYards", "statValue": 1849}, {"season": 2024, "team": "Wisconsin", "conference": "Big Ten", "statName": "rushingYardsOpponent", "statValue": 1988}, {"season": 2024, "team": "Wisconsin", "conference": "Big Ten", "statName": "sacks", "statValue": 17}, {"season": 2024, "team": "Wisconsin", "conference": "Big Ten", "statName": "sacksOpponent", "statValue": 13}, {"season": 2024, "team": "Wisconsin", "conference": "Big Ten", "statName": "tacklesForLoss", "statValue": 42}, {"season": 2024, "team": "Wisconsin", "conference": "Big Ten", "statName": "tacklesForLossOpponent", "statValue": 47}, {"season": 2024, "team": "Wisconsin", "conference": "Big Ten", "statName": "thirdDownConversions", "statValue": 57}, {"season": 2024, "team": "Wisconsin", "conference": "Big Ten", "statName": "thirdDownConversionsOpponent", "statValue": 62}, {"season": 2024, "team": "Wisconsin", "conference": "Big Ten", "statName": "thirdDowns", "statValue": 159}, {"season": 2024, "team": "Wisconsin", "conference": "Big Ten", "statName": "thirdDownsOpponent", "statValue": 158}, {"season": 2024, "team": "Wisconsin", "conference": "Big Ten", "statName": "totalYards", "statValue": 4209}, {"season": 2024, "team": "Wisconsin", "conference": "Big Ten", "statName": "totalYardsOpponent", "statValue": 4120}, {"season": 2024, "team": "Wisconsin", "conference": "Big Ten", "statName": "turnovers", "statValue": 18}, {"season": 2024, "team": "Wisconsin", "conference": "Big Ten", "statName": "turnoversOpponent", "statValue": 12}]